ampy/__init__.py
ampy/__version__.py
ampy/cli.py
ampy/files.py
ampy/pyboard.py
wonderbits_ampy-1.1.5.dist-info/LICENSE
wonderbits_ampy-1.1.5.dist-info/METADATA
wonderbits_ampy-1.1.5.dist-info/WHEEL
wonderbits_ampy-1.1.5.dist-info/entry_points.txt
wonderbits_ampy-1.1.5.dist-info/top_level.txt
wonderbits_ampy-1.1.5.dist-info/RECORD
