Metadata-Version: 2.1
Name: wonderbits-ampy
Version: 1.1.5
Summary: ampy (Adafruit MicroPython tool) is a command line tool to interact with a CircuitPython or MicroPython board over a serial connection.
Home-page: https://github.com/BigCircleLaw/ampy
Author: mfe
Author-email: 794557226@qq.com
License: MIT
Keywords: adafruit ampy hardware micropython circuitpython
Platform: UNKNOWN
Classifier: Development Status :: 4 - Beta
Classifier: Intended Audience :: Developers
Classifier: License :: OSI Approved :: MIT License
Classifier: Programming Language :: Python :: 2
Classifier: Programming Language :: Python :: 2.6
Classifier: Programming Language :: Python :: 2.7
Classifier: Programming Language :: Python :: 3
Classifier: Programming Language :: Python :: 3.3
Classifier: Programming Language :: Python :: 3.4
Classifier: Programming Language :: Python :: 3.5
Requires-Dist: click
Requires-Dist: pyserial
Requires-Dist: python-dotenv
